{
  "menu_patterns": [
    {
      "style": "standard",
      "courses": [
        "entrada",
        "plato_principal",
        "postre"
      ],
      "dietary_options": [
        "regular",
        "vegetariano"
      ],
      "price_range": [
        50.0,
        100.0
      ],
      "guest_count_range": [
        50,
        200
      ],
      "success_rate": 0.8,
      "last_used": "2025-06-15T05:52:29.807203",
      "usage_count": 0
    },
    {
      "style": "premium",
      "courses": [
        "entrada",
        "sopa",
        "plato_principal",
        "ensalada",
        "postre"
      ],
      "dietary_options": [
        "regular",
        "vegetariano",
        "vegano"
      ],
      "price_range": [
        100.0,
        200.0
      ],
      "guest_count_range": [
        30,
        150
      ],
      "success_rate": 0.9,
      "last_used": "2025-06-15T05:52:29.807216",
      "usage_count": 0
    }
  ]
}